LICENSE
MANIFEST.in
NEWS.txt
README.rst
setup.py
src/ipython_sparksql.egg-info/PKG-INFO
src/ipython_sparksql.egg-info/SOURCES.txt
src/ipython_sparksql.egg-info/dependency_links.txt
src/ipython_sparksql.egg-info/not-zip-safe
src/ipython_sparksql.egg-info/requires.txt
src/ipython_sparksql.egg-info/top_level.txt
src/sql/__init__.py
src/sql/column_guesser.py
src/sql/connection.py
src/sql/magic.py
src/sql/parse.py
src/sql/run.py