Metadata-Version: 1.1
Name: ipython-sparksql
Version: 0.3.9
Summary: RDBMS access via IPython
Home-page: https://pypi.python.org/pypi/ipython-sparksql
Author: similarface
Author-email: similarface@gmail.com
License: MIT
Keywords: database ipython postgresql mysql
Platform: UNKNOWN
Classifier: Development Status :: 3 - Alpha
Classifier: Environment :: Console
Classifier: License :: OSI Approved :: MIT License
Classifier: Topic :: Database
Classifier: Topic :: Database :: Front-Ends
Classifier: Programming Language :: Python :: 3
Classifier: Programming Language :: Python :: 2
